pycatzao/__init__.py
pycatzao/_utils.py
pycatzao/_version.py
pycatzao/compress.py
pycatzao/decoder.py
pycatzao/encoder.py
pycatzao/utils.py
pycatzao-1.2.3.dist-info/licenses/LICENSE
pycatzao-1.2.3.dist-info/METADATA
pycatzao-1.2.3.dist-info/WHEEL
pycatzao-1.2.3.dist-info/top_level.txt
pycatzao-1.2.3.dist-info/RECORD
