Metadata-Version: 2.4
Name: pycatzao
Version: 1.2.3
Summary: A pure Python library for encoding, decoding and compressing Asterix CAT240 messages.
Home-page: https://github.com/DLR-KN/pycatzao
Author: Nis Meinert
Author-email: nis.meinert@dlr.de
Requires-Python: >=3.10
License-File: LICENSE
Requires-Dist: numpy
Requires-Dist: tqdm
Provides-Extra: dev
Requires-Dist: pre-commit; extra == "dev"
Requires-Dist: pytest; extra == "dev"
Requires-Dist: pytest-cov; extra == "dev"
Requires-Dist: sphinx; extra == "dev"
Dynamic: author
Dynamic: author-email
Dynamic: description
Dynamic: description-content-type
Dynamic: home-page
Dynamic: license-file
Dynamic: provides-extra
Dynamic: requires-dist
Dynamic: requires-python
Dynamic: summary
